<?xml version="1.0"?><entity><entities><entity pageid="1087" ns="0" title="Q778" lastrevid="202761378" modified="2015-03-09T19:31:54Z" id="Q778" type="item"><aliases><alias language="es" value="Mancomunidad de las Bahamas" /><alias language="en" value="Bahamas" /><alias language="en" value="Commonwealth of the Bahamas" /><alias language="pt-br" value="Comunidade das Bahamas" /><alias language="pt-br" value="Baamas" /><alias language="hu" value="Bahamai Közösség" /></aliases><descriptions><description language="en" value="country in North America" /><description language="es" value="país del Caribe" /><description language="fr" value="état insulaire au large des Caraïbes" /><description language="it" value="stato insulare dell&#039;America centrale" /><description language="ru" value="страна в Северной Америке" /><description language="de" value="Inselstaat im Atlantik, Teil der Westindischen Inseln" /><description language="ilo" value="pagilian idiay Amianan nga Amerika" /><description language="nb" value="land i Karibia" /><description language="pt-br" value="país insular da América do Norte" /><description language="sr" value="острвска држава у Атлантском океану" /><description language="sr-ec" value="острвска држава у Атлантском океану" /><description language="sr-el" value="ostrvska država u Atlantskom okeanu" /><description language="zh-hans" value="北美洲国家" /><description language="he" value="מדינה באיים הקריבים" /><description language="hu" value="szigetország a Karib-térségben" /><description language="uk" value="держава на 700 островах біля південно-східного узбережжя Флориди і на північ від Куби" /><description language="nl" value="land in Noord-Amerika" /></descriptions><labels><label language="en" value="The Bahamas" /><label language="de" value="Bahamas" /><label language="fr" value="Bahamas" /><label language="es" value="Bahamas" /><label language="en-ca" value="The Bahamas" /><label language="en-gb" value="The Bahamas" /><label language="nl" value="Bahama&#039;s" /><label language="af" value="Bahamas" /><label language="am" value="ባሃማስ" /><label language="an" value="Bahamas" /><label language="ar" value="البهاما" /><label language="arz" value="باهاماس" /><label language="ast" value="Les Bahames" /><label language="az" value="Baham adaları" /><label language="bcl" value="Bahamas" /><label language="be" value="Багамскія Астравы" /><label language="bg" value="Бахамски острови" /><label language="bm" value="Bahamasi" /><label language="bn" value="বাহামা দ্বীপপুঞ্জ" /><label language="bo" value="བ་ཧ་མཱ་སི།" /><label language="bpy" value="বাহামা" /><label language="br" value="Bahamas" /><label language="bs" value="Bahami" /><label language="ca" value="Bahames" /><label language="ce" value="Багаман Гlайреш" /><label language="ceb" value="Bahamas" /><label language="ckb" value="بەھاما" /><label language="cs" value="Bahamy" /><label language="cv" value="Пахам утравĕсем" /><label language="cy" value="Y Bahamas" /><label language="da" value="Bahamas" /><label language="diq" value="Bahama" /><label language="dsb" value="Bahamy" /><label language="dv" value="ބަހާމަސް" /><label language="dz" value="བཱ་ཧ་མས྄།" /><label language="ee" value="Bahamas" /><label language="el" value="Μπαχάμες" /><label language="eo" value="Bahamoj" /><label language="et" value="Bahama" /><label language="eu" value="Bahamak" /><label language="ext" value="Baamas" /><label language="fa" value="باهاما" /><label language="fi" value="Bahama" /><label language="fo" value="Bahamaoyggjar" /><label language="frp" value="Bahamas" /><label language="frr" value="Bahaamas" /><label language="fy" value="Bahama&#039;s" /><label language="ga" value="Na Bahámaí" /><label language="gag" value="Bahamalar" /><label language="gd" value="Na h-Eileanan Bhathama" /><label language="gl" value="Bahamas" /><label language="gv" value="Ny Bahamaghyn" /><label language="hak" value="Pâ-hâ-mâ" /><label language="he" value="איי בהאמה" /><label language="hi" value="बहामास" /><label language="hif" value="The Bahamas" /><label language="hr" value="Bahami" /><label language="hsb" value="Bahamy" /><label language="ht" value="Bahamas" /><label language="hu" value="Bahama-szigetek" /><label language="hy" value="Բահամյան Կղզիներ" /><label language="ia" value="Bahamas" /><label language="id" value="Bahama" /><label language="ilo" value="Bahamas" /><label language="io" value="Bahama" /><label language="is" value="Bahamaeyjar" /><label language="it" value="Bahamas" /><label language="ja" value="バハマ" /><label language="jv" value="Bahama" /><label language="ka" value="ბაჰამის კუნძულები" /><label language="kk" value="Бағамалар" /><label language="kn" value="ಬಹಾಮಾಸ್" /><label language="ko" value="바하마" /><label language="ku" value="Bahama" /><label language="kw" value="Ynysow Bahama" /><label language="la" value="Insulae Bahamenses" /><label language="lb" value="Bahamas" /><label language="li" value="Bahama&#039;s" /><label language="lij" value="Bahamas" /><label language="lmo" value="Bahamas" /><label language="ln" value="Bahamas" /><label language="lt" value="Bahamos" /><label language="lv" value="Bahamas" /><label language="mg" value="Bahamasy" /><label language="mk" value="Бахами" /><label language="ml" value="ബഹാമാസ്" /><label language="mr" value="बहामास" /><label language="mrj" value="Багамвлӓ" /><label language="ms" value="Bahamas" /><label language="mwl" value="Bahamas" /><label language="my" value="ဘဟားမားနိုင်ငံ" /><label language="na" value="Bahamat" /><label language="nah" value="Bahamas" /><label language="nds" value="Bahamas" /><label language="nn" value="Bahamas" /><label language="nov" value="Bahamas" /><label language="oc" value="Bahamas" /><label language="or" value="ବାହାମା" /><label language="os" value="Багамы сакъадæхтæ" /><label language="pam" value="Bahamas" /><label language="pap" value="Bahamas" /><label language="pih" value="Bahaamas" /><label language="pl" value="Bahamy" /><label language="pms" value="Bahamas" /><label language="pnb" value="باہاما" /><label language="pt" value="Bahamas" /><label language="qu" value="Bahamakuna" /><label language="rm" value="Bahamas" /><label language="ro" value="Bahamas" /><label language="ru" value="Багамские Острова" /><label language="rue" value="Багамы" /><label language="rw" value="Bahamasi" /><label language="sa" value="बहामास" /><label language="sah" value="Баhамалар" /><label language="scn" value="Bahamas" /><label language="sco" value="The Bahamas" /><label language="se" value="Bahama" /><label language="sh" value="Bahami" /><label language="sk" value="Bahamy" /><label language="sl" value="Bahami" /><label language="so" value="Bahamas" /><label language="sq" value="Bahamet" /><label language="sr" value="Бахаме" /><label language="ss" value="IBhahamasi" /><label language="stq" value="Bahamas" /><label language="su" value="Bahama" /><label language="sv" value="Bahamas" /><label language="sw" value="Bahamas" /><label language="ta" value="பகாமாசு" /><label language="te" value="బహామాస్" /><label language="tet" value="Bahamas" /><label language="th" value="ประเทศบาฮามาส" /><label language="tk" value="Bagama Adalary" /><label language="tl" value="Bahamas" /><label language="tr" value="Bahamalar" /><label language="tt" value="Багамалар" /><label language="ug" value="باھاما" /><label language="uk" value="Багамські Острови" /><label language="ur" value="بہاماس" /><label language="uz" value="Bagamalar" /><label language="vec" value="Bahamas" /><label language="vi" value="Bahamas" /><label language="vo" value="Bahamuäns" /><label language="war" value="Bahamas" /><label language="wo" value="Bahamas" /><label language="xal" value="Багамуд Арлин Ниицән" /><label language="yi" value="באהאמאס" /><label language="yo" value="Àwọn Bàhámà" /><label language="zh" value="巴哈马" /><label language="zh-cn" value="巴哈马" /><label language="zh-hans" value="巴哈马" /><label language="zh-hant" value="巴哈马" /><label language="nb" value="Bahamas" /><label language="pt-br" value="Bahamas" /><label language="vep" value="Bagaman Sared" /><label language="bxr" value="Баһаамын аралууд" /><label language="mt" value="Baħamas" /><label language="ay" value="Bahamas" /><label language="gn" value="Va&#039;ama" /><label language="mhr" value="Багаме" /><label language="ba" value="Багамы" /><label language="ace" value="Bahama" /><label language="sr-ec" value="Бахаме" /><label language="sr-el" value="Bahame" /><label language="zea" value="Bahama&#039;s" /><label language="si" value="බහමාස්" /><label language="pa" value="ਬਹਾਮਾਸ" /><label language="crh-latn" value="Bahamalar" /><label language="gsw" value="Bahamas" /><label language="vro" value="Bahama" /><label language="sgs" value="Bahamas" /><label language="nan" value="Bahamas" /><label language="be-tarask" value="Багамы" /><label language="rup" value="Bahamas" /><label language="yue" value="巴哈馬" /><label language="kab" value="Bahamas" /><label language="sn" value="The Bahamas" /><label language="ne" value="बहामस" /><label language="tg" value="Баҳамас" /><label language="de-ch" value="Bahamas" /><label language="om" value="Bahamaas" /><label language="tokipona" value="ma Pawama" /><label language="cdo" value="Bahamas" /><label language="xmf" value="ბაჰამიშ კოკეფი" /></labels><claims><property id="P190"><claim id="Q778$cde28e78-4fd9-4aca-c64e-4bc8d7615c28" type="statement" rank="normal"><mainsnak snaktype="value" property="P190" datatype="wikibase-item"><datavalue type="wikibase-entityid"><value entity-type="item" numeric-id="468557" /></datavalue></mainsnak><qualifiers /><qualifiers-order /></claim></property><property id="P1151"><claim id="Q778$9f1edca3-4ff1-0f41-0f0e-031d2b8bc29d" type="statement" rank="normal"><mainsnak snaktype="value" property="P1151" datatype="wikibase-item"><datavalue type="wikibase-entityid"><value entity-type="item" numeric-id="11144046" /></datavalue></mainsnak><qualifiers /><qualifiers-order /></claim></property><property id="P35"><claim id="q778$04514BA7-42F8-406D-97CE-BEC5FDE7B841" type="statement" rank="normal"><mainsnak snaktype="value" property="P35" datatype="wikibase-item"><datavalue type="wikibase-entityid"><value entity-type="item" numeric-id="9682" /></datavalue></mainsnak><qualifiers /><qualifiers-order /></claim></property><property id="P31"><claim id="q778$9DFB7161-1A2C-4B49-B9A9-5ECC621BC1EB" type="statement" rank="normal"><mainsnak snaktype="value" property="P31" datatype="wikibase-item"><datavalue type="wikibase-entityid"><value entity-type="item" numeric-id="202686" /></datavalue></mainsnak><qualifiers /><qualifiers-order /></claim><claim id="Q778$7CA7756A-9EED-421A-B495-999265CBD155" type="statement" rank="normal"><mainsnak snaktype="value" property="P31" datatype="wikibase-item"><datavalue type="wikibase-entityid"><value entity-type="item" numeric-id="7275" /></datavalue></mainsnak><qualifiers /><qualifiers-order /></claim><claim id="Q778$667df090-4c4b-b650-e7f5-ad9fbfda4fa3" type="statement" rank="normal"><mainsnak snaktype="value" property="P31" datatype="wikibase-item"><datavalue type="wikibase-entityid"><value entity-type="item" numeric-id="112099" /></datavalue></mainsnak><qualifiers /><qualifiers-order /></claim></property><property id="P36"><claim id="q778$52E8E3FE-40BE-4408-855F-8C1284E702B0" type="statement" rank="normal"><mainsnak snaktype="value" property="P36" datatype="wikibase-item"><datavalue type="wikibase-entityid"><value entity-type="item" numeric-id="2467" /></datavalue></mainsnak><qualifiers /><qualifiers-order /></claim></property><property id="P37"><claim id="q778$0202AD2D-61E8-476D-95B3-EC5180A8095C" type="statement" rank="normal"><mainsnak snaktype="value" property="P37" datatype="wikibase-item"><datavalue type="wikibase-entityid"><value entity-type="item" numeric-id="1860" /></datavalue></mainsnak><qualifiers /><qualifiers-order /></claim></property><property id="P38"><claim id="q778$AFABCCE8-CD4D-447A-AD74-2D4B9AE740C8" type="statement" rank="normal"><mainsnak snaktype="value" property="P38" datatype="wikibase-item"><datavalue type="wikibase-entityid"><value entity-type="item" numeric-id="194339" /></datavalue></mainsnak><qualifiers /><qualifiers-order /></claim></property><property id="P41"><claim id="q778$824EFF2D-DCEB-440F-BB6B-F5B336B436EA" type="statement" rank="normal"><mainsnak snaktype="value" property="P41" datatype="commonsMedia"><datavalue value="Flag of the Bahamas.svg" type="string" /></mainsnak><qualifiers /><qualifiers-order /></claim></property><property id="P78"><claim id="q778$FB15F35A-676D-469F-B8C4-C7270A550580" type="statement" rank="normal"><mainsnak snaktype="value" property="P78" datatype="wikibase-item"><datavalue type="wikibase-entityid"><value entity-type="item" numeric-id="40514" /></datavalue></mainsnak><qualifiers /><qualifiers-order /></claim></property><property id="P297"><claim id="q778$27559C0B-0381-405D-B66B-886409002E22" type="statement" rank="normal"><mainsnak snaktype="value" property="P297" datatype="string"><datavalue value="BS" type="string" /></mainsnak><qualifiers /><qualifiers-order /></claim></property><property id="P298"><claim id="q778$715B97D9-1E31-4542-A5C9-5B668278275E" type="statement" rank="normal"><mainsnak snaktype="value" property="P298" datatype="string"><datavalue value="BHS" type="string" /></mainsnak><qualifiers /><qualifiers-order /></claim></property><property id="P299"><claim id="q778$324CCA0B-012E-4E2A-9037-840347232743" type="statement" rank="normal"><mainsnak snaktype="value" property="P299" datatype="string"><datavalue value="044" type="string" /></mainsnak><qualifiers /><qualifiers-order /></claim></property><property id="P94"><claim id="q778$4E0ACF18-9A02-4D84-AED8-E1F2F920C5AB" type="statement" rank="normal"><mainsnak snaktype="value" property="P94" datatype="commonsMedia"><datavalue value="Coat of arms of the Bahamas.svg" type="string" /></mainsnak><qualifiers /><qualifiers-order /></claim></property><property id="P373"><claim id="q778$76DECAD8-4FC9-4C9E-AD01-741D2AB37E2F" type="statement" rank="normal"><mainsnak snaktype="value" property="P373" datatype="string"><datavalue value="Bahamas" type="string" /></mainsnak><qualifiers /><qualifiers-order /><references><reference hash="dbe2189e7b0d3953de6f69cc1cc88109a79605a4"><snaks><property id="P143"><snak snaktype="value" property="P143" datatype="wikibase-item"><datavalue type="wikibase-entityid"><value entity-type="item" numeric-id="8449" /></datavalue></snak></property></snaks><snaks-order><property>P143</property></snaks-order></reference></references></claim></property><property id="P163"><claim id="q778$fb8adf10-48e0-c0d1-3eae-00cd19839ac7" type="statement" rank="normal"><mainsnak snaktype="value" property="P163" datatype="wikibase-item"><datavalue type="wikibase-entityid"><value entity-type="item" numeric-id="103447" /></datavalue></mainsnak><qualifiers /><qualifiers-order /></claim></property><property id="P6"><claim id="q778$01298325-35C8-49C7-B989-3D8D5B48AFFF" type="statement" rank="normal"><mainsnak snaktype="value" property="P6" datatype="wikibase-item"><datavalue type="wikibase-entityid"><value entity-type="item" numeric-id="57705" /></datavalue></mainsnak><qualifiers /><qualifiers-order /></claim></property><property id="P30"><claim id="q778$AB3E13A2-0CB3-40F2-AC7B-6DB9025129F8" type="statement" rank="normal"><mainsnak snaktype="value" property="P30" datatype="wikibase-item"><datavalue type="wikibase-entityid"><value entity-type="item" numeric-id="664609" /></datavalue></mainsnak><qualifiers /><qualifiers-order /></claim></property><property id="P194"><claim id="q778$d9df5800-477c-42fe-72c1-da38167f83d1" type="statement" rank="normal"><mainsnak snaktype="value" property="P194" datatype="wikibase-item"><datavalue type="wikibase-entityid"><value entity-type="item" numeric-id="1572486" /></datavalue></mainsnak><qualifiers /><qualifiers-order /></claim></property><property id="P85"><claim id="q778$acb569d9-42ef-af20-1d04-bfb0f95854df" type="statement" rank="normal"><mainsnak snaktype="value" property="P85" datatype="wikibase-item"><datavalue type="wikibase-entityid"><value entity-type="item" numeric-id="40807" /></datavalue></mainsnak><qualifiers /><qualifiers-order /></claim></property><property id="P625"><claim id="q778$C9822D7A-FF46-4CF1-8D35-1427308A4B97" type="statement" rank="normal"><mainsnak snaktype="value" property="P625" datatype="globe-coordinate"><datavalue type="globecoordinate"><value latitude="23.916667" longitude="-77.666667" altitude="" precision="1.0E-5" globe="http://www.wikidata.org/entity/Q2" /></datavalue></mainsnak><qualifiers /><qualifiers-order /><references><reference hash="223f43a7229297bd67ffab922174f80c722fff1a"><snaks><property id="P143"><snak snaktype="value" property="P143" datatype="wikibase-item"><datavalue type="wikibase-entityid"><value entity-type="item" numeric-id="10000" /></datavalue></snak></property></snaks><snaks-order><property>P143</property></snaks-order></reference></references></claim></property><property id="P150"><claim id="q778$412e9d19-4347-8e40-ed1c-12ec8759120a" type="statement" rank="normal"><mainsnak snaktype="value" property="P150" datatype="wikibase-item"><datavalue type="wikibase-entityid"><value entity-type="item" numeric-id="341919" /></datavalue></mainsnak><qualifiers /><qualifiers-order /></claim><claim id="q778$257ca408-4cbd-48a4-1429-1d34d9ec6906" type="statement" rank="normal"><mainsnak snaktype="value" property="P150" datatype="wikibase-item"><datavalue type="wikibase-entityid"><value entity-type="item" numeric-id="827173" /></datavalue></mainsnak><qualifiers /><qualifiers-order /></claim><claim id="q778$dda9242b-4c18-b005-0c2b-06256ad571fd" type="statement" rank="normal"><mainsnak snaktype="value" property="P150" datatype="wikibase-item"><datavalue type="wikibase-entityid"><value entity-type="item" numeric-id="863476" /></datavalue></mainsnak><qualifiers /><qualifiers-order /></claim><claim id="q778$c2f81a61-4c41-61e7-4a7a-7de0a647acbf" type="statement" rank="normal"><mainsnak snaktype="value" property="P150" datatype="wikibase-item"><datavalue type="wikibase-entityid"><value entity-type="item" numeric-id="2525298" /></datavalue></mainsnak><qualifiers /><qualifiers-order /></claim><claim id="q778$a04c9ad8-4277-c94c-f9f2-038d4bd005a7" type="statement" rank="normal"><mainsnak snaktype="value" property="P150" datatype="wikibase-item"><datavalue type="wikibase-entityid"><value entity-type="item" numeric-id="1050154" /></datavalue></mainsnak><qualifiers /><qualifiers-order /></claim><claim id="q778$942ea58b-4e1e-ed1f-bc10-3f86e1fa9a4c" type="statement" rank="normal"><mainsnak snaktype="value" property="P150" datatype="wikibase-item"><datavalue type="wikibase-entityid"><value entity-type="item" numeric-id="2525371" /></datavalue></mainsnak><qualifiers /><qualifiers-order /></claim><claim id="q778$ba3e514d-4d39-ea70-2c02-729197215084" type="statement" rank="normal"><mainsnak snaktype="value" property="P150" datatype="wikibase-item"><datavalue type="wikibase-entityid"><value entity-type="item" numeric-id="2096558" /></datavalue></mainsnak><qualifiers /><qualifiers-order /></claim><claim id="q778$61261a76-46df-b781-88af-672c447f7cc6" type="statement" rank="normal"><mainsnak snaktype="value" property="P150" datatype="wikibase-item"><datavalue type="wikibase-entityid"><value entity-type="item" numeric-id="938518" /></datavalue></mainsnak><qualifiers /><qualifiers-order /></claim><claim id="q778$d1f4620e-40fc-0cb2-2aad-91f0886a14d2" type="statement" rank="normal"><mainsnak snaktype="value" property="P150" datatype="wikibase-item"><datavalue type="wikibase-entityid"><value entity-type="item" numeric-id="867573" /></datavalue></mainsnak><qualifiers /><qualifiers-order /></claim><claim id="q778$edf06aa6-4aac-9034-ab34-4e032cc22bba" type="statement" rank="normal"><mainsnak snaktype="value" property="P150" datatype="wikibase-item"><datavalue type="wikibase-entityid"><value entity-type="item" numeric-id="1140993" /></datavalue></mainsnak><qualifiers /><qualifiers-order /></claim><claim id="q778$27e15faf-4880-a197-e0f6-62ab4ea0b433" type="statement" rank="normal"><mainsnak snaktype="value" property="P150" datatype="wikibase-item"><datavalue type="wikibase-entityid"><value entity-type="item" numeric-id="2630334" /></datavalue></mainsnak><qualifiers /><qualifiers-order /></claim><claim id="q778$9dcb346f-4403-622d-17ff-3edffc27c643" type="statement" rank="normal"><mainsnak snaktype="value" property="P150" datatype="wikibase-item"><datavalue type="wikibase-entityid"><value entity-type="item" numeric-id="1385577" /></datavalue></mainsnak><qualifiers /><qualifiers-order /></claim><claim id="q778$581c678d-43c7-d73e-2976-98063d99e540" type="statement" rank="normal"><mainsnak snaktype="value" property="P150" datatype="wikibase-item"><datavalue type="wikibase-entityid"><value entity-type="item" numeric-id="2524373" /></datavalue></mainsnak><qualifiers /><qualifiers-order /></claim><claim id="q778$f351f828-454a-430d-585e-58b2be970321" type="statement" rank="normal"><mainsnak snaktype="value" property="P150" datatype="wikibase-item"><datavalue type="wikibase-entityid"><value entity-type="item" numeric-id="2357510" /></datavalue></mainsnak><qualifiers /><qualifiers-order /></claim><claim id="q778$390c198b-460e-11bb-1847-0c808c943e28" type="statement" rank="normal"><mainsnak snaktype="value" property="P150" datatype="wikibase-item"><datavalue type="wikibase-entityid"><value entity-type="item" numeric-id="2699709" /></datavalue></mainsnak><qualifiers /><qualifiers-order /></claim><claim id="q778$6da0726d-4d25-f6f4-22f4-36059f8795d7" type="statement" rank="normal"><mainsnak snaktype="value" property="P150" datatype="wikibase-item"><datavalue type="wikibase-entityid"><value entity-type="item" numeric-id="1353668" /></datavalue></mainsnak><qualifiers /><qualifiers-order /></claim><claim id="q778$5710f4ca-4a8e-1974-81f0-3bcd21c21446" type="statement" rank="normal"><mainsnak snaktype="value" property="P150" datatype="wikibase-item"><datavalue type="wikibase-entityid"><value entity-type="item" numeric-id="890879" /></datavalue></mainsnak><qualifiers /><qualifiers-order /></claim><claim id="q778$42839b52-45a8-6960-7124-d975ac0728c2" type="statement" rank="normal"><mainsnak snaktype="value" property="P150" datatype="wikibase-item"><datavalue type="wikibase-entityid"><value entity-type="item" numeric-id="2702334" /></datavalue></mainsnak><qualifiers /><qualifiers-order /></claim><claim id="q778$8d2c9963-4814-7e75-3f4e-41cfead030c1" type="statement" rank="normal"><mainsnak snaktype="value" property="P150" datatype="wikibase-item"><datavalue type="wikibase-entityid"><value entity-type="item" numeric-id="1540098" /></datavalue></mainsnak><qualifiers /><qualifiers-order /></claim><claim id="q778$75a0caa3-4650-9b06-917e-5f2861c66c33" type="statement" rank="normal"><mainsnak snaktype="value" property="P150" datatype="wikibase-item"><datavalue type="wikibase-entityid"><value entity-type="item" numeric-id="2702345" /></datavalue></mainsnak><qualifiers /><qualifiers-order /></claim><claim id="q778$3aae6f22-4b61-b0d2-ae7c-de914274da1d" type="statement" rank="normal"><mainsnak snaktype="value" property="P150" datatype="wikibase-item"><datavalue type="wikibase-entityid"><value entity-type="item" numeric-id="623327" /></datavalue></mainsnak><qualifiers /><qualifiers-order /></claim><claim id="q778$cc9c811a-40d1-84ab-b725-f34c8b22ba8c" type="statement" rank="normal"><mainsnak snaktype="value" property="P150" datatype="wikibase-item"><datavalue type="wikibase-entityid"><value entity-type="item" numeric-id="2699411" /></datavalue></mainsnak><qualifiers /><qualifiers-order /></claim><claim id="q778$95e0313e-4063-4df8-f0bf-ff40e2f4b2de" type="statement" rank="normal"><mainsnak snaktype="value" property="P150" datatype="wikibase-item"><datavalue type="wikibase-entityid"><value entity-type="item" numeric-id="2705535" /></datavalue></mainsnak><qualifiers /><qualifiers-order /></claim><claim id="q778$204b569b-40b5-6eff-863c-8d8ee82cd159" type="statement" rank="normal"><mainsnak snaktype="value" property="P150" datatype="wikibase-item"><datavalue type="wikibase-entityid"><value entity-type="item" numeric-id="1532634" /></datavalue></mainsnak><qualifiers /><qualifiers-order /></claim><claim id="q778$9ba9df15-4239-230e-6572-4c29e5b1ed1c" type="statement" rank="normal"><mainsnak snaktype="value" property="P150" datatype="wikibase-item"><datavalue type="wikibase-entityid"><value entity-type="item" numeric-id="1859950" /></datavalue></mainsnak><qualifiers /><qualifiers-order /></claim><claim id="q778$8ad48d6d-45c3-3f75-1d4d-f19524b71f65" type="statement" rank="normal"><mainsnak snaktype="value" property="P150" datatype="wikibase-item"><datavalue type="wikibase-entityid"><value entity-type="item" numeric-id="845540" /></datavalue></mainsnak><qualifiers /><qualifiers-order /></claim><claim id="q778$1c3c91e6-4a05-644e-e1eb-3bab4fb05321" type="statement" rank="normal"><mainsnak snaktype="value" property="P150" datatype="wikibase-item"><datavalue type="wikibase-entityid"><value entity-type="item" numeric-id="2703192" /></datavalue></mainsnak><qualifiers /><qualifiers-order /></claim><claim id="q778$f2e1ca75-4142-3a22-1bb6-747b9b5f27dc" type="statement" rank="normal"><mainsnak snaktype="value" property="P150" datatype="wikibase-item"><datavalue type="wikibase-entityid"><value entity-type="item" numeric-id="2408672" /></datavalue></mainsnak><qualifiers /><qualifiers-order /></claim><claim id="q778$64c3b78a-4493-995b-2669-2a3aab28a4fe" type="statement" rank="normal"><mainsnak snaktype="value" property="P150" datatype="wikibase-item"><datavalue type="wikibase-entityid"><value entity-type="item" numeric-id="2699715" /></datavalue></mainsnak><qualifiers /><qualifiers-order /></claim><claim id="q778$73c6726e-4e00-b88f-2512-074a65947a5f" type="statement" rank="normal"><mainsnak snaktype="value" property="P150" datatype="wikibase-item"><datavalue type="wikibase-entityid"><value entity-type="item" numeric-id="1771681" /></datavalue></mainsnak><qualifiers /><qualifiers-order /></claim><claim id="q778$0607322e-46cc-be9d-0ffd-f7532e06cb2c" type="statement" rank="normal"><mainsnak snaktype="value" property="P150" datatype="wikibase-item"><datavalue type="wikibase-entityid"><value entity-type="item" numeric-id="2702338" /></datavalue></mainsnak><qualifiers /><qualifiers-order /></claim><claim id="q778$22a92c24-4b34-559c-61a1-067238a4c022" type="statement" rank="normal"><mainsnak snaktype="value" property="P150" datatype="wikibase-item"><datavalue type="wikibase-entityid"><value entity-type="item" numeric-id="858513" /></datavalue></mainsnak><qualifiers /><qualifiers-order /></claim></property><property id="P463"><claim id="q778$DBCD0CE2-C277-41F1-AC38-C38DEF9B0756" type="statement" rank="normal"><mainsnak snaktype="value" property="P463" datatype="wikibase-item"><datavalue type="wikibase-entityid"><value entity-type="item" numeric-id="1065" /></datavalue></mainsnak><qualifiers /><qualifiers-order /></claim><claim id="q778$CA30C95E-7A57-456A-B80F-CC9FE3D6888B" type="statement" rank="normal"><mainsnak snaktype="value" property="P463" datatype="wikibase-item"><datavalue type="wikibase-entityid"><value entity-type="item" numeric-id="7785" /></datavalue></mainsnak><qualifiers /><qualifiers-order /></claim><claim id="q778$E8A77C15-3583-4AD4-BD72-1FAEE6F236B3" type="statement" rank="normal"><mainsnak snaktype="value" property="P463" datatype="wikibase-item"><datavalue type="wikibase-entityid"><value entity-type="item" numeric-id="205995" /></datavalue></mainsnak><qualifiers /><qualifiers-order /></claim></property><property id="P910"><claim id="Q778$3E742975-F947-4548-B0A8-A8800959B9C5" type="statement" rank="normal"><mainsnak snaktype="value" property="P910" datatype="wikibase-item"><datavalue type="wikibase-entityid"><value entity-type="item" numeric-id="8846444" /></datavalue></mainsnak><qualifiers /><qualifiers-order /></claim></property><property id="P242"><claim id="Q778$1c1c2ac2-4bc9-1343-9950-2c0d1e3a62b4" type="statement" rank="normal"><mainsnak snaktype="value" property="P242" datatype="commonsMedia"><datavalue value="LocationBahamas.svg" type="string" /></mainsnak><qualifiers /><qualifiers-order /></claim></property><property id="P948"><claim id="Q778$ad7c541e-48dc-da5b-c76c-028434fd6ee1" type="statement" rank="normal"><mainsnak snaktype="value" property="P948" datatype="commonsMedia"><datavalue value="Jaws Beach, Bahamas banner.jpg" type="string" /></mainsnak><qualifiers /><qualifiers-order /></claim></property><property id="P237"><claim id="Q778$D64A287D-48BD-4087-86BB-C7CF1084F801" type="statement" rank="normal"><mainsnak snaktype="value" property="P237" datatype="wikibase-item"><datavalue type="wikibase-entityid"><value entity-type="item" numeric-id="273093" /></datavalue></mainsnak><qualifiers /><qualifiers-order /><references><reference hash="d6e3ab4045fb3f3feea77895bc6b27e663fc878a"><snaks><property id="P143"><snak snaktype="value" property="P143" datatype="wikibase-item"><datavalue type="wikibase-entityid"><value entity-type="item" numeric-id="206855" /></datavalue></snak></property></snaks><snaks-order><property>P143</property></snaks-order></reference></references></claim></property><property id="P349"><claim id="Q778$42BEF980-74F2-4665-B05C-8D99A97F8007" type="statement" rank="normal"><mainsnak snaktype="value" property="P349" datatype="string"><datavalue value="00575689" type="string" /></mainsnak><qualifiers /><qualifiers-order /></claim></property><property id="P856"><claim id="Q778$907840E2-12DE-4C7D-A124-5AFDF25A4397" type="statement" rank="normal"><mainsnak snaktype="value" property="P856" datatype="url"><datavalue value="http://www.bahamas.gov.bs" type="string" /></mainsnak><qualifiers /><qualifiers-order /><references><reference hash="7eb64cf9621d34c54fd4bd040ed4b61a88c4a1a0"><snaks><property id="P143"><snak snaktype="value" property="P143" datatype="wikibase-item"><datavalue type="wikibase-entityid"><value entity-type="item" numeric-id="328" /></datavalue></snak></property></snaks><snaks-order><property>P143</property></snaks-order></reference></references></claim></property><property id="P214"><claim id="Q778$2AC8347D-0A15-463B-9755-3E8E5E1697CB" type="statement" rank="normal"><mainsnak snaktype="value" property="P214" datatype="string"><datavalue value="254170310" type="string" /></mainsnak><qualifiers /><qualifiers-order /><references><reference hash="a51d6594fee36c7452eaed2db35a4833613a7078"><snaks><property id="P143"><snak snaktype="value" property="P143" datatype="wikibase-item"><datavalue type="wikibase-entityid"><value entity-type="item" numeric-id="54919" /></datavalue></snak></property></snaks><snaks-order><property>P143</property></snaks-order></reference></references></claim></property><property id="P998"><claim id="Q778$1797C588-D7A6-4F8A-AC7B-4BB3766FDF99" type="statement" rank="normal"><mainsnak snaktype="value" property="P998" datatype="string"><datavalue value="Regional/Caribbean/Bahamas/" type="string" /></mainsnak><qualifiers /><qualifiers-order /></claim></property><property id="P984"><claim id="Q778$5B7604B0-8374-4CC2-88D3-045B7BC71122" type="statement" rank="normal"><mainsnak snaktype="value" property="P984" datatype="string"><datavalue value="BAH" type="string" /></mainsnak><qualifiers /><qualifiers-order /><references><reference hash="d6e3ab4045fb3f3feea77895bc6b27e663fc878a"><snaks><property id="P143"><snak snaktype="value" property="P143" datatype="wikibase-item"><datavalue type="wikibase-entityid"><value entity-type="item" numeric-id="206855" /></datavalue></snak></property></snaks><snaks-order><property>P143</property></snaks-order></reference></references></claim></property><property id="P982"><claim id="Q778$FC475B2F-0A24-4626-A903-09094CC6F0C5" type="statement" rank="normal"><mainsnak snaktype="value" property="P982" datatype="string"><datavalue value="f8b33963-7364-33be-8c6c-5ab2e1075ae1" type="string" /></mainsnak><qualifiers /><qualifiers-order /><references><reference hash="73057782312f850e2ed69c4c28ad162f57f6d390"><snaks><property id="P248"><snak snaktype="value" property="P248" datatype="wikibase-item"><datavalue type="wikibase-entityid"><value entity-type="item" numeric-id="14005" /></datavalue></snak></property></snaks><snaks-order><property>P248</property></snaks-order></reference></references></claim></property><property id="P17"><claim id="Q778$9F65AE34-70A7-4CD0-B867-41554B73435B" type="statement" rank="normal"><mainsnak snaktype="value" property="P17" datatype="wikibase-item"><datavalue type="wikibase-entityid"><value entity-type="item" numeric-id="778" /></datavalue></mainsnak><qualifiers /><qualifiers-order /></claim></property><property id="P646"><claim id="Q778$C700DB81-3D82-42FE-A7D0-A32566F98F85" type="statement" rank="normal"><mainsnak snaktype="value" property="P646" datatype="string"><datavalue value="/m/0160w" type="string" /></mainsnak><qualifiers /><qualifiers-order /><references><reference hash="b923b0d68beb300866b87ead39f61e63ec30d8af"><snaks><property id="P248"><snak snaktype="value" property="P248" datatype="wikibase-item"><datavalue type="wikibase-entityid"><value entity-type="item" numeric-id="15241312" /></datavalue></snak></property><property id="P577"><snak snaktype="value" property="P577" datatype="time"><datavalue type="time"><value time="+00000002013-10-28T00:00:00Z" timezone="0" before="0" after="0" precision="11" calendarmodel="http://www.wikidata.org/entity/Q1985727" /></datavalue></snak></property></snaks><snaks-order><property>P248</property><property>P577</property></snaks-order></reference></references></claim></property><property id="P901"><claim id="Q778$C536FAD9-34EF-4F20-A6DD-9B4B566AA259" type="statement" rank="normal"><mainsnak snaktype="value" property="P901" datatype="string"><datavalue value="BF" type="string" /></mainsnak><qualifiers /><qualifiers-order /><references><reference hash="efc47ca21c9bb45ffc2ed36fde1428e38a40db83"><snaks><property id="P143"><snak snaktype="value" property="P143" datatype="wikibase-item"><datavalue type="wikibase-entityid"><value entity-type="item" numeric-id="328" /></datavalue></snak></property><property id="P854"><snak snaktype="value" property="P854" datatype="url"><datavalue value="https://en.wikipedia.org/w/index.php?title=List_of_FIPS_country_codes&amp;oldid=588315474" type="string" /></snak></property><property id="P364"><snak snaktype="value" property="P364" datatype="wikibase-item"><datavalue type="wikibase-entityid"><value entity-type="item" numeric-id="1860" /></datavalue></snak></property><property id="P357"><snak snaktype="value" property="P357" datatype="string"><datavalue value="List of FIPS country codes" type="string" /></snak></property><property id="P813"><snak snaktype="value" property="P813" datatype="time"><datavalue type="time"><value time="+00000002013-12-30T00:00:00Z" timezone="0" before="0" after="0" precision="11" calendarmodel="http://www.wikidata.org/entity/Q1985727" /></datavalue></snak></property></snaks><snaks-order><property>P143</property><property>P854</property><property>P364</property><property>P357</property><property>P813</property></snaks-order></reference></references></claim></property><property id="P935"><claim id="Q778$F6BF9492-80EA-4251-9037-7D05A0A0C3DA" type="statement" rank="normal"><mainsnak snaktype="value" property="P935" datatype="string"><datavalue value="The Bahamas" type="string" /></mainsnak><qualifiers /><qualifiers-order /></claim></property><property id="P610"><claim id="Q778$285e67f7-4f0d-46d4-e57b-245afc16a878" type="statement" rank="normal"><mainsnak snaktype="value" property="P610" datatype="wikibase-item"><datavalue type="wikibase-entityid"><value entity-type="item" numeric-id="746274" /></datavalue></mainsnak><qualifiers /><qualifiers-order /></claim></property><property id="P1566"><claim id="Q778$C9AEB513-5BDE-4205-8FE3-AB1571F7E5D4" type="statement" rank="normal"><mainsnak snaktype="value" property="P1566" datatype="string"><datavalue value="3572887" type="string" /></mainsnak><qualifiers /><qualifiers-order /></claim></property><property id="P47"><claim id="Q778$61B950CB-799F-45C2-8E95-684B030CAF72" type="statement" rank="normal"><mainsnak snaktype="value" property="P47" datatype="wikibase-item"><datavalue type="wikibase-entityid"><value entity-type="item" numeric-id="30" /></datavalue></mainsnak><qualifiers /><qualifiers-order /></claim></property><property id="P227"><claim id="Q778$482FF44D-ADAE-48DD-98C6-1E2C135C2DD6" type="statement" rank="normal"><mainsnak snaktype="value" property="P227" datatype="string"><datavalue value="4069081-7" type="string" /></mainsnak><qualifiers /><qualifiers-order /><references><reference hash="004ec6fbee857649acdbdbad4f97b2c8571df97b"><snaks><property id="P143"><snak snaktype="value" property="P143" datatype="wikibase-item"><datavalue type="wikibase-entityid"><value entity-type="item" numeric-id="48183" /></datavalue></snak></property></snaks><snaks-order><property>P143</property></snaks-order></reference></references></claim></property><property id="P421"><claim id="Q778$09C16C89-A917-49DC-B12B-C8F4F7267DA8" type="statement" rank="normal"><mainsnak snaktype="value" property="P421" datatype="wikibase-item"><datavalue type="wikibase-entityid"><value entity-type="item" numeric-id="5390" /></datavalue></mainsnak><qualifiers /><qualifiers-order /></claim></property><property id="P1465"><claim id="Q778$7a27155f-4b52-6a30-a8de-bc216c885eb8" type="statement" rank="normal"><mainsnak snaktype="value" property="P1465" datatype="wikibase-item"><datavalue type="wikibase-entityid"><value entity-type="item" numeric-id="8365688" /></datavalue></mainsnak><qualifiers /><qualifiers-order /></claim></property><property id="P1740"><claim id="Q778$DB64C3CB-F285-42AD-ADA8-3A65ACA636CE" type="statement" rank="normal"><mainsnak snaktype="value" property="P1740" datatype="wikibase-item"><datavalue type="wikibase-entityid"><value entity-type="item" numeric-id="6296742" /></datavalue></mainsnak><qualifiers /><qualifiers-order /></claim></property></claims><sitelinks><sitelink site="commonswiki" title="The Bahamas"><badges /></sitelink><sitelink site="enwikivoyage" title="Bahamas"><badges /></sitelink><sitelink site="eswikivoyage" title="Bahamas"><badges /></sitelink><sitelink site="frwikivoyage" title="Bahamas"><badges /></sitelink><sitelink site="hewikivoyage" title="איי בהאמה"><badges /></sitelink><sitelink site="itwikivoyage" title="Bahamas"><badges /></sitelink><sitelink site="nlwikivoyage" title="Bahama&#039;s"><badges /></sitelink><sitelink site="plwikivoyage" title="Bahamy"><badges /></sitelink><sitelink site="ptwikivoyage" title="Bahamas"><badges /></sitelink><sitelink site="ruwikivoyage" title="Багамские Острова"><badges /></sitelink><sitelink site="svwikivoyage" title="Bahamas"><badges /></sitelink><sitelink site="ukwikivoyage" title="Багамські Острови"><badges /></sitelink><sitelink site="viwikivoyage" title="Bahamas"><badges /></sitelink><sitelink site="zhwikivoyage" title="巴哈马"><badges /></sitelink><sitelink site="dewikivoyage" title="Bahamas"><badges><badge>Q17559452</badge></badges></sitelink><sitelink site="enwiki" title="The Bahamas"><badges /></sitelink><sitelink site="dewiki" title="Bahamas"><badges /></sitelink><sitelink site="frwiki" title="Bahamas"><badges /></sitelink><sitelink site="eswiki" title="Bahamas"><badges /></sitelink><sitelink site="ruwiki" title="Багамские Острова"><badges /></sitelink><sitelink site="itwiki" title="Bahamas"><badges /></sitelink><sitelink site="jawiki" title="バハマ"><badges /></sitelink><sitelink site="nlwiki" title="Bahama&#039;s"><badges /></sitelink><sitelink site="plwiki" title="Bahamy"><badges /></sitelink><sitelink site="ptwiki" title="Bahamas"><badges /></sitelink><sitelink site="zhwiki" title="巴哈马"><badges /></sitelink><sitelink site="svwiki" title="Bahamas"><badges /></sitelink><sitelink site="fawiki" title="باهاما"><badges /></sitelink><sitelink site="hewiki" title="איי בהאמה"><badges /></sitelink><sitelink site="trwiki" title="Bahamalar"><badges /></sitelink><sitelink site="huwiki" title="Bahama-szigetek"><badges /></sitelink><sitelink site="fiwiki" title="Bahama"><badges><badge>Q17559452</badge></badges></sitelink><sitelink site="viwiki" title="Bahamas"><badges /></sitelink><sitelink site="nowiki" title="Bahamas"><badges /></sitelink><sitelink site="ukwiki" title="Багамські Острови"><badges /></sitelink><sitelink site="kowiki" title="바하마"><badges /></sitelink><sitelink site="cawiki" title="Bahames"><badges /></sitelink><sitelink site="cswiki" title="Bahamy"><badges /></sitelink><sitelink site="srwiki" title="Бахаме"><badges /></sitelink><sitelink site="rowiki" title="Bahamas"><badges /></sitelink><sitelink site="idwiki" title="Bahama"><badges /></sitelink><sitelink site="dawiki" title="Bahamas"><badges /></sitelink><sitelink site="simplewiki" title="The Bahamas"><badges /></sitelink><sitelink site="bgwiki" title="Бахамски острови"><badges /></sitelink><sitelink site="acewiki" title="Bahama"><badges /></sitelink><sitelink site="afwiki" title="Bahamas"><badges /></sitelink><sitelink site="alswiki" title="Bahamas"><badges /></sitelink><sitelink site="amwiki" title="ባሃማስ"><badges /></sitelink><sitelink site="anwiki" title="Bahamas"><badges /></sitelink><sitelink site="arzwiki" title="باهاماس"><badges /></sitelink><sitelink site="astwiki" title="Les Bahames"><badges /></sitelink><sitelink site="aywiki" title="Bahamas"><badges /></sitelink><sitelink site="azwiki" title="Baham adaları"><badges /></sitelink><sitelink site="bawiki" title="Багам Утрауҙары"><badges /></sitelink><sitelink site="bat_smgwiki" title="Bahamas"><badges /></sitelink><sitelink site="bclwiki" title="Bahamas"><badges /></sitelink><sitelink site="bewiki" title="Багамскія Астравы"><badges /></sitelink><sitelink site="be_x_oldwiki" title="Багамы"><badges /></sitelink><sitelink site="bmwiki" title="Bahamasi"><badges /></sitelink><sitelink site="bnwiki" title="বাহামা দ্বীপপুঞ্জ"><badges /></sitelink><sitelink site="bowiki" title="བ་ཧ་མཱ་སི།"><badges /></sitelink><sitelink site="bpywiki" title="বাহামা"><badges /></sitelink><sitelink site="brwiki" title="Bahamas"><badges /></sitelink><sitelink site="bswiki" title="Bahami"><badges /></sitelink><sitelink site="bxrwiki" title="Бахамын аралууд"><badges /></sitelink><sitelink site="cewiki" title="Багаман гӀайренаш"><badges /></sitelink><sitelink site="cebwiki" title="Bahamas"><badges /></sitelink><sitelink site="ckbwiki" title="بەھاما"><badges /></sitelink><sitelink site="crhwiki" title="Bahamalar"><badges /></sitelink><sitelink site="cvwiki" title="Пахам утравĕсем"><badges /></sitelink><sitelink site="cywiki" title="Y Bahamas"><badges /></sitelink><sitelink site="diqwiki" title="Bahama"><badges /></sitelink><sitelink site="dsbwiki" title="Bahamy"><badges /></sitelink><sitelink site="dvwiki" title="ބަހާމަސް"><badges /></sitelink><sitelink site="dzwiki" title="བཱ་ཧ་མས྄།"><badges /></sitelink><sitelink site="eewiki" title="Bahamas"><badges /></sitelink><sitelink site="elwiki" title="Μπαχάμες"><badges /></sitelink><sitelink site="eowiki" title="Bahamoj"><badges /></sitelink><sitelink site="etwiki" title="Bahama"><badges /></sitelink><sitelink site="euwiki" title="Bahamak"><badges /></sitelink><sitelink site="extwiki" title="Baamas"><badges /></sitelink><sitelink site="fiu_vrowiki" title="Bahama"><badges /></sitelink><sitelink site="fowiki" title="Bahamaoyggjar"><badges /></sitelink><sitelink site="frpwiki" title="Bahamas"><badges /></sitelink><sitelink site="frrwiki" title="Bahaamas"><badges /></sitelink><sitelink site="fywiki" title="Bahama&#039;s"><badges /></sitelink><sitelink site="gawiki" title="Na Bahámaí"><badges /></sitelink><sitelink site="gagwiki" title="Bahamalar"><badges /></sitelink><sitelink site="gdwiki" title="Na h-Eileanan Bhathama"><badges /></sitelink><sitelink site="glwiki" title="Bahamas"><badges /></sitelink><sitelink site="gnwiki" title="Va&#039;ama"><badges /></sitelink><sitelink site="gvwiki" title="Ny Bahamaghyn"><badges /></sitelink><sitelink site="hakwiki" title="Pâ-hâ-mâ"><badges /></sitelink><sitelink site="hiwiki" title="बहामास"><badges /></sitelink><sitelink site="hifwiki" title="The Bahamas"><badges /></sitelink><sitelink site="hrwiki" title="Bahami"><badges /></sitelink><sitelink site="hsbwiki" title="Bahamy"><badges /></sitelink><sitelink site="htwiki" title="Bahamas"><badges /></sitelink><sitelink site="hywiki" title="Բահամյան Կղզիներ"><badges /></sitelink><sitelink site="iawiki" title="Bahamas"><badges /></sitelink><sitelink site="ilowiki" title="Bahamas"><badges /></sitelink><sitelink site="iowiki" title="Bahama"><badges /></sitelink><sitelink site="iswiki" title="Bahamaeyjar"><badges /></sitelink><sitelink site="jvwiki" title="Bahama"><badges /></sitelink><sitelink site="kawiki" title="ბაჰამის კუნძულები"><badges><badge>Q17437796</badge></badges></sitelink><sitelink site="kabwiki" title="Bahamas"><badges /></sitelink><sitelink site="kkwiki" title="Багам аралдары"><badges /></sitelink><sitelink site="knwiki" title="ಬಹಾಮಾಸ್"><badges /></sitelink><sitelink site="kuwiki" title="Bahama"><badges /></sitelink><sitelink site="kwwiki" title="Ynysow Bahama"><badges /></sitelink><sitelink site="lawiki" title="Insulae Bahamenses"><badges /></sitelink><sitelink site="lbwiki" title="Bahamas"><badges /></sitelink><sitelink site="liwiki" title="Bahama&#039;s"><badges /></sitelink><sitelink site="lijwiki" title="Bahamas"><badges /></sitelink><sitelink site="lmowiki" title="Bahamas"><badges /></sitelink><sitelink site="lnwiki" title="Bahamas"><badges /></sitelink><sitelink site="ltwiki" title="Bahamos"><badges /></sitelink><sitelink site="lvwiki" title="Bahamas"><badges /></sitelink><sitelink site="mgwiki" title="Bahamasy"><badges /></sitelink><sitelink site="mhrwiki" title="Багаме"><badges /></sitelink><sitelink site="mkwiki" title="Бахами"><badges /></sitelink><sitelink site="mlwiki" title="ബഹാമാസ്"><badges /></sitelink><sitelink site="mrwiki" title="बहामास"><badges /></sitelink><sitelink site="mrjwiki" title="Багамвлӓ"><badges /></sitelink><sitelink site="mswiki" title="Bahamas"><badges /></sitelink><sitelink site="mtwiki" title="Baħamas"><badges /></sitelink><sitelink site="mwlwiki" title="Bahamas"><badges /></sitelink><sitelink site="mywiki" title="ဘဟားမားနိုင်ငံ"><badges /></sitelink><sitelink site="nawiki" title="Bahamat"><badges /></sitelink><sitelink site="nahwiki" title="Bahamas"><badges /></sitelink><sitelink site="ndswiki" title="Bahamas"><badges /></sitelink><sitelink site="newiki" title="बहामस"><badges /></sitelink><sitelink site="nnwiki" title="Bahamas"><badges /></sitelink><sitelink site="novwiki" title="Bahamas"><badges /></sitelink><sitelink site="ocwiki" title="Bahamas"><badges /></sitelink><sitelink site="omwiki" title="Bahamaas"><badges /></sitelink><sitelink site="orwiki" title="ବାହାମା"><badges /></sitelink><sitelink site="oswiki" title="Багамы сакъадæхтæ"><badges /></sitelink><sitelink site="pawiki" title="ਬਹਾਮਾਸ"><badges /></sitelink><sitelink site="pamwiki" title="Bahamas"><badges /></sitelink><sitelink site="papwiki" title="Bahamas"><badges /></sitelink><sitelink site="pihwiki" title="Bahaamas"><badges /></sitelink><sitelink site="pmswiki" title="Bahamas"><badges /></sitelink><sitelink site="pnbwiki" title="باہاما"><badges /></sitelink><sitelink site="quwiki" title="Bahamakuna"><badges /></sitelink><sitelink site="rmwiki" title="Bahamas"><badges /></sitelink><sitelink site="roa_rupwiki" title="Bahamas"><badges /></sitelink><sitelink site="ruewiki" title="Багамы"><badges /></sitelink><sitelink site="rwwiki" title="Bahamasi"><badges /></sitelink><sitelink site="sawiki" title="बहामास"><badges /></sitelink><sitelink site="sahwiki" title="Багама Холбоһуга"><badges /></sitelink><sitelink site="scnwiki" title="Bahamas"><badges /></sitelink><sitelink site="scowiki" title="The Bahamas"><badges /></sitelink><sitelink site="sewiki" title="Bahama"><badges /></sitelink><sitelink site="shwiki" title="Bahami"><badges /></sitelink><sitelink site="siwiki" title="බහමාස්"><badges /></sitelink><sitelink site="skwiki" title="Bahamy"><badges /></sitelink><sitelink site="slwiki" title="Bahami"><badges /></sitelink><sitelink site="snwiki" title="The Bahamas"><badges /></sitelink><sitelink site="sowiki" title="Bahamas"><badges /></sitelink><sitelink site="sqwiki" title="Bahamet"><badges /></sitelink><sitelink site="sswiki" title="IBhahamasi"><badges /></sitelink><sitelink site="stqwiki" title="Bahamas"><badges /></sitelink><sitelink site="suwiki" title="Bahama"><badges /></sitelink><sitelink site="swwiki" title="Bahamas"><badges /></sitelink><sitelink site="tawiki" title="பகாமாசு"><badges /></sitelink><sitelink site="tewiki" title="బహామాస్"><badges /></sitelink><sitelink site="tetwiki" title="Bahamas"><badges /></sitelink><sitelink site="tgwiki" title="Баҳамас"><badges /></sitelink><sitelink site="thwiki" title="ประเทศบาฮามาส"><badges /></sitelink><sitelink site="tkwiki" title="Bagama Adalary"><badges /></sitelink><sitelink site="tlwiki" title="Bahamas"><badges /></sitelink><sitelink site="ttwiki" title="Багамалар"><badges /></sitelink><sitelink site="ugwiki" title="باھاما"><badges /></sitelink><sitelink site="urwiki" title="بہاماس"><badges /></sitelink><sitelink site="uzwiki" title="Bagamalar"><badges /></sitelink><sitelink site="vecwiki" title="Bahamas"><badges /></sitelink><sitelink site="vepwiki" title="Bagaman Sared"><badges /></sitelink><sitelink site="vowiki" title="Bahamuäns"><badges /></sitelink><sitelink site="warwiki" title="Bahamas"><badges /></sitelink><sitelink site="wowiki" title="Bahamas"><badges /></sitelink><sitelink site="xalwiki" title="Багамуд Арлин Ниицән"><badges /></sitelink><sitelink site="xmfwiki" title="ბაჰამიშ კოკეფი"><badges /></sitelink><sitelink site="yiwiki" title="באהאמאס"><badges /></sitelink><sitelink site="yowiki" title="Àwọn Bàhámà"><badges /></sitelink><sitelink site="zeawiki" title="Bahama&#039;s"><badges /></sitelink><sitelink site="zh_min_nanwiki" title="Bahamas"><badges /></sitelink><sitelink site="zh_yuewiki" title="巴哈馬"><badges /></sitelink><sitelink site="fawikivoyage" title="باهاما"><badges /></sitelink><sitelink site="cdowiki" title="Bahamas"><badges /></sitelink><sitelink site="arwiki" title="باهاماس"><badges /></sitelink><sitelink site="plwikiquote" title="Bahamy"><badges /></sitelink></sitelinks></entity></entities></entity>