<?xml version="1.0"?><entity><entities><entity pageid="30967" ns="0" title="Q27561" lastrevid="204049130" modified="2015-03-14T21:31:30Z" id="Q27561" type="item"><aliases><alias language="eu" value="BES uharteak" /><alias language="fr" value="Bonaire, Saint-Eustache et Saba" /><alias language="fr" value="Îles BES" /><alias language="es" value="Karibe Neerlandès" /><alias language="es" value="Caribisch Nederland" /><alias language="es" value="Islas BES" /><alias language="frr" value="BES eilunen" /><alias language="frr" value="BES-eilun" /><alias language="frr" value="Aparte gemeen" /><alias language="frr" value="Besondere Gemeinde" /><alias language="af" value="Karibies-Nederland" /><alias language="af" value="BES-Eilande" /><alias language="oc" value="Illas BES" /><alias language="lv" value="Karību Nīderlande" /><alias language="it" value="Caraibi Olandesi" /><alias language="it" value="Municipalità olandesi d&#039;oltremare" /><alias language="de" value="BES-Inseln" /><alias language="de" value="Karibische Niederlande" /><alias language="ja" value="オランダ領カリブ" /><alias language="ja" value="BES諸島" /><alias language="ja" value="カリブ・オランダ" /><alias language="nl" value="Caraibisch Nederland" /><alias language="nl" value="BES eilanden" /><alias language="nl" value="BES-eilanden" /><alias language="nl" value="Caraïbisch Nederland" /><alias language="nl" value="Bijzondere gemeente" /><alias language="ru" value="БЭС-острова" /><alias language="ru" value="Нидерландские Карибские острова" /><alias language="ru" value="Карибская Голландия" /><alias language="ru" value="Острова Бонайре, Синт-Эстатиус и Саба" /><alias language="ru" value="Карибские Нидерланды" /><alias language="ru" value="Острова БЭС" /><alias language="ru" value="Острова БЕС" /><alias language="ru" value="Бонайре, Синт-Эстатиус и Саба" /><alias language="ru" value="Карибские Нидерландские острова" /><alias language="ru" value="Нидерланды Карибские" /><alias language="ru" value="БЕС-острова" /><alias language="ru" value="Бонайре, Саба и Синт-Эстатиус" /><alias language="fy" value="BES-eilannen" /><alias language="ca" value="Carib neerlandès" /><alias language="uk" value="Острови BES" /><alias language="nn" value="BES-øyane" /><alias language="nn" value="Bonaire, Sint Eustatius og Saba" /><alias language="cs" value="BES ostrovy" /><alias language="fa" value="کارائیب هلند" /><alias language="fa" value="هلند کارائیب" /><alias language="ur" value="Bonaire, Saint Eustatius and Saba" /><alias language="lt" value="Karibų Nyderlandai" /><alias language="en" value="BES islands" /><alias language="nb" value="BES-øyene" /><alias language="nb" value="Bonaire, Saint Eustatius og Saba" /><alias language="nb" value="Bonaire, Sint Eustatius og Saba" /><alias language="nb" value="BES" /><alias language="el" value="Καραϊβική Ολλανδία" /><alias language="hu" value="Királyság-szigetek (Bonaire, Saba, Sint Eustatius)" /><alias language="hu" value="BES-szigetek" /></aliases><descriptions><description language="en" value="grouping of the Caribbean islands of Bonaire, Sint Eustatius, and Saba, part of the Netherlands" /><description language="nb" value="gruppering av de karibiske øyene Bonaire, Sint Eustatius og Saba, som er del av Nederland" /><description language="nl" value="benaming van de Nederlandse bijzondere gemeenten (eilanden) Bonaire, Sint Eustatius en Saba in de Caraïben" /><description language="es" value="región conformada por las islas de Bonaire, San Eustaquio y Saba en los Paises Bajos" /><description language="de" value="Besonderen Gemeinden der Niederlande: Bonaire, Sint Eustatius und Saba" /><description language="fr" value="regroupement des îles néerlandaises de Bonaire, Saint-Eustache et Saba" /><description language="it" value="isole caraibiche olandesi" /><description language="ru" value="островное владение Нидерландов в Карибском море, в архипелаге Малых Антильских островов в Вест-Индии" /><description language="hu" value="Hollandia különleges státusú szigetei a Karib-tengeren" /></descriptions><labels><label language="zh" value="荷蘭加勒比區" /><label language="pl" value="Niderlandy Karaibskie" /><label language="eu" value="Karibeko Herbehereak" /><label language="ko" value="네덜란드령 카리브 해 지역" /><label language="fr" value="Pays-Bas caribéens" /><label language="bs" value="Karipska Holandija" /><label language="es" value="Caribe Neerlandés" /><label language="lad" value="Karibe Neerlandez" /><label language="frr" value="BES-eilunen" /><label language="af" value="Karibies Nederland" /><label language="oc" value="Païses Basses Caribencs" /><label language="lv" value="Bonaire, Sintēstatiusa un Saba" /><label language="it" value="Isole BES" /><label language="id" value="Kepulauan BES" /><label language="de" value="Karibische Niederlande" /><label language="ja" value="ボネール、シント・ユースタティウスおよびサバ" /><label language="vi" value="Caribe Hà Lan" /><label language="sv" value="Karibiska Nederländerna" /><label language="nl" value="Caribisch Nederland" /><label language="pt" value="Países Baixos Caribenhos" /><label language="ru" value="Бонэйр, Синт-Эстатиус и Саба" /><label language="sr" value="Карипска Холандија" /><label language="en" value="Caribbean Netherlands" /><label language="fy" value="Karibysk Nederlân" /><label language="ca" value="Illes BES" /><label language="uk" value="Нідерландські Карибські острови" /><label language="nn" value="Karibisk Nederland" /><label language="cs" value="Karibské Nizozemsko" /><label language="fa" value="جزایر کارائیب هلند" /><label language="ur" value="کیریبین نیدرلینڈز" /><label language="ka" value="კარიბის ნიდერლანდები" /><label language="lt" value="BES salos" /><label language="ar" value="الجزر الكاريبية الهولندية" /><label language="eo" value="Kariba Nederlando" /><label language="nb" value="Karibisk Nederland" /><label language="pnb" value="کریبین نیدرلینڈز" /><label language="pa" value="ਕੈਰੀਬੀਆਈ ਨੀਦਰਲੈਂਡ" /><label language="li" value="Caribisch Nederland" /><label language="el" value="Καραϊβικές Κάτω Χώρες" /><label language="en-gb" value="Caribbean Netherlands" /><label language="sco" value="Caribbean Netherlands" /><label language="mk" value="Карипска Холандија" /><label language="hu" value="Karibi Hollandia" /></labels><claims><property id="P17"><claim id="q27561$B6B889A3-3CB2-4695-9EA0-2D901F98AFC7" type="statement" rank="normal"><mainsnak snaktype="value" property="P17" datatype="wikibase-item"><datavalue type="wikibase-entityid"><value entity-type="item" numeric-id="55" /></datavalue></mainsnak><qualifiers /><qualifiers-order /></claim></property><property id="P297"><claim id="q27561$52BF99F4-0E85-4055-B808-1AA6374B8FED" type="statement" rank="normal"><mainsnak snaktype="value" property="P297" datatype="string"><datavalue value="BQ" type="string" /></mainsnak><qualifiers /><qualifiers-order /></claim></property><property id="P298"><claim id="q27561$77E42448-58A6-4B53-B949-F64A52488036" type="statement" rank="normal"><mainsnak snaktype="value" property="P298" datatype="string"><datavalue value="BES" type="string" /></mainsnak><qualifiers /><qualifiers-order /></claim></property><property id="P299"><claim id="q27561$FD30D8B9-B796-42EC-8826-F10758FACCF1" type="statement" rank="normal"><mainsnak snaktype="value" property="P299" datatype="string"><datavalue value="535" type="string" /></mainsnak><qualifiers /><qualifiers-order /></claim></property><property id="P373"><claim id="q27561$330EB83E-2237-4707-BC9F-3786799CC2EE" type="statement" rank="normal"><mainsnak snaktype="value" property="P373" datatype="string"><datavalue value="Caribbean Netherlands" type="string" /></mainsnak><qualifiers /><qualifiers-order /></claim></property><property id="P41"><claim id="q27561$1BC7A6D8-C97E-42EF-9C27-C87FF755F6F8" type="statement" rank="normal"><mainsnak snaktype="value" property="P41" datatype="commonsMedia"><datavalue value="Flag of the Netherlands.svg" type="string" /></mainsnak><qualifiers /><qualifiers-order /><references><reference hash="dbe2189e7b0d3953de6f69cc1cc88109a79605a4"><snaks><property id="P143"><snak snaktype="value" property="P143" datatype="wikibase-item"><datavalue type="wikibase-entityid"><value entity-type="item" numeric-id="8449" /></datavalue></snak></property></snaks><snaks-order><property>P143</property></snaks-order></reference></references></claim></property><property id="P242"><claim id="q27561$81fa3336-4038-4001-e585-eea10366f252" type="statement" rank="normal"><mainsnak snaktype="value" property="P242" datatype="commonsMedia"><datavalue value="BES islands location map.svg" type="string" /></mainsnak><qualifiers /><qualifiers-order /></claim></property><property id="P30"><claim id="q27561$BFC5F46A-064B-4655-82F0-F7ABCF407A98" type="statement" rank="normal"><mainsnak snaktype="value" property="P30" datatype="wikibase-item"><datavalue type="wikibase-entityid"><value entity-type="item" numeric-id="664609" /></datavalue></mainsnak><qualifiers /><qualifiers-order /></claim></property><property id="P527"><claim id="q27561$5574121a-4bd2-d4a2-c87c-8de2c11dfe13" type="statement" rank="normal"><mainsnak snaktype="value" property="P527" datatype="wikibase-item"><datavalue type="wikibase-entityid"><value entity-type="item" numeric-id="25396" /></datavalue></mainsnak><qualifiers /><qualifiers-order /></claim><claim id="q27561$753a9c2d-483f-05ef-95c6-a245b3e76505" type="statement" rank="normal"><mainsnak snaktype="value" property="P527" datatype="wikibase-item"><datavalue type="wikibase-entityid"><value entity-type="item" numeric-id="26180" /></datavalue></mainsnak><qualifiers /><qualifiers-order /></claim><claim id="q27561$a8582685-4f7b-edcf-6626-82c01e472500" type="statement" rank="normal"><mainsnak snaktype="value" property="P527" datatype="wikibase-item"><datavalue type="wikibase-entityid"><value entity-type="item" numeric-id="25528" /></datavalue></mainsnak><qualifiers /><qualifiers-order /></claim></property><property id="P361"><claim id="q27561$a8815bbe-41d2-df40-2b14-9f98bc7b4506" type="statement" rank="normal"><mainsnak snaktype="value" property="P361" datatype="wikibase-item"><datavalue type="wikibase-entityid"><value entity-type="item" numeric-id="5317255" /></datavalue></mainsnak><qualifiers /><qualifiers-order /></claim></property><property id="P78"><claim id="q27561$5aa38354-4bb6-30a9-4a26-2cfdc301bb2d" type="statement" rank="normal"><mainsnak snaktype="value" property="P78" datatype="wikibase-item"><datavalue type="wikibase-entityid"><value entity-type="item" numeric-id="142380" /></datavalue></mainsnak><qualifiers /><qualifiers-order /></claim><claim id="Q27561$90ca31d5-4e42-1ef7-5f3f-b6c679bf0bac" type="statement" rank="preferred"><mainsnak snaktype="value" property="P78" datatype="wikibase-item"><datavalue type="wikibase-entityid"><value entity-type="item" numeric-id="493202" /></datavalue></mainsnak><qualifiers /><qualifiers-order /></claim><claim id="Q27561$7839010a-4754-6516-7957-c70f851f43e6" type="statement" rank="deprecated"><mainsnak snaktype="value" property="P78" datatype="wikibase-item"><datavalue type="wikibase-entityid"><value entity-type="item" numeric-id="40342" /></datavalue></mainsnak><qualifiers /><qualifiers-order /></claim></property><property id="P36"><claim id="q27561$54cf524c-4f09-c391-ff47-852a398e9663" type="statement" rank="normal"><mainsnak snaktype="novalue" property="P36" /><qualifiers /><qualifiers-order /></claim></property><property id="P625"><claim id="q27561$a3e38e7f-4b67-aa5c-ac1d-dce66a7e1aa4" type="statement" rank="normal"><mainsnak snaktype="value" property="P625" datatype="globe-coordinate"><datavalue type="globecoordinate"><value latitude="12.183333333333" longitude="-68.233333333333" altitude="" precision="0.016666666666667" globe="http://www.wikidata.org/entity/Q2" /></datavalue></mainsnak><qualifiers /><qualifiers-order /></claim></property><property id="P474"><claim id="q27561$53258525-4f71-8e2c-07b3-319f298fa622" type="statement" rank="normal"><mainsnak snaktype="value" property="P474" datatype="string"><datavalue value="+599" type="string" /></mainsnak><qualifiers /><qualifiers-order /></claim></property><property id="P402"><claim id="q27561$07f3fc8f-46af-7dd4-ed8a-d03044290141" type="statement" rank="normal"><mainsnak snaktype="value" property="P402" datatype="string"><datavalue value="1216720" type="string" /></mainsnak><qualifiers /><qualifiers-order /></claim></property><property id="P910"><claim id="Q27561$524a7543-4708-2842-5632-07d5ecbbc77b" type="statement" rank="normal"><mainsnak snaktype="value" property="P910" datatype="wikibase-item"><datavalue type="wikibase-entityid"><value entity-type="item" numeric-id="8344109" /></datavalue></mainsnak><qualifiers /><qualifiers-order /></claim></property><property id="P94"><claim id="q27561$297AD6FE-CA10-4BBD-83C8-0A275B9C5E09" type="statement" rank="normal"><mainsnak snaktype="value" property="P94" datatype="commonsMedia"><datavalue value="State coat of arms of the Netherlands.svg" type="string" /></mainsnak><qualifiers /><qualifiers-order /><references><reference hash="7eb64cf9621d34c54fd4bd040ed4b61a88c4a1a0"><snaks><property id="P143"><snak snaktype="value" property="P143" datatype="wikibase-item"><datavalue type="wikibase-entityid"><value entity-type="item" numeric-id="328" /></datavalue></snak></property></snaks><snaks-order><property>P143</property></snaks-order></reference></references></claim></property><property id="P38"><claim id="Q27561$DA6B841C-EB83-42AC-889E-3CB2D0FDE8A1" type="statement" rank="normal"><mainsnak snaktype="value" property="P38" datatype="wikibase-item"><datavalue type="wikibase-entityid"><value entity-type="item" numeric-id="4917" /></datavalue></mainsnak><qualifiers /><qualifiers-order /><references><reference hash="d6e3ab4045fb3f3feea77895bc6b27e663fc878a"><snaks><property id="P143"><snak snaktype="value" property="P143" datatype="wikibase-item"><datavalue type="wikibase-entityid"><value entity-type="item" numeric-id="206855" /></datavalue></snak></property></snaks><snaks-order><property>P143</property></snaks-order></reference></references></claim></property><property id="P610"><claim id="Q27561$675ff482-49f2-3808-3256-126dc2dba9b7" type="statement" rank="normal"><mainsnak snaktype="value" property="P610" datatype="wikibase-item"><datavalue type="wikibase-entityid"><value entity-type="item" numeric-id="1301834" /></datavalue></mainsnak><qualifiers /><qualifiers-order /></claim></property><property id="P31"><claim id="Q27561$0d4ffcf9-464e-e3d4-22ff-936269fe9d2d" type="statement" rank="normal"><mainsnak snaktype="value" property="P31" datatype="wikibase-item"><datavalue type="wikibase-entityid"><value entity-type="item" numeric-id="82794" /></datavalue></mainsnak><qualifiers /><qualifiers-order /></claim></property><property id="P421"><claim id="Q27561$ab27cce9-48b3-483a-830e-784455b46f99" type="statement" rank="normal"><mainsnak snaktype="value" property="P421" datatype="wikibase-item"><datavalue type="wikibase-entityid"><value entity-type="item" numeric-id="2085376" /></datavalue></mainsnak><qualifiers /><qualifiers-order /></claim></property><property id="P646"><claim id="Q27561$B27F55A6-FDA4-4D7A-8296-24FE293A146E" type="statement" rank="normal"><mainsnak snaktype="value" property="P646" datatype="string"><datavalue value="/m/0bwhs8r" type="string" /></mainsnak><qualifiers /><qualifiers-order /><references><reference hash="b923b0d68beb300866b87ead39f61e63ec30d8af"><snaks><property id="P248"><snak snaktype="value" property="P248" datatype="wikibase-item"><datavalue type="wikibase-entityid"><value entity-type="item" numeric-id="15241312" /></datavalue></snak></property><property id="P577"><snak snaktype="value" property="P577" datatype="time"><datavalue type="time"><value time="+00000002013-10-28T00:00:00Z" timezone="0" before="0" after="0" precision="11" calendarmodel="http://www.wikidata.org/entity/Q1985727" /></datavalue></snak></property></snaks><snaks-order><property>P248</property><property>P577</property></snaks-order></reference></references></claim></property><property id="P982"><claim id="Q27561$5A74E4D5-63CC-4AFE-8264-2CCA309F0E08" type="statement" rank="normal"><mainsnak snaktype="value" property="P982" datatype="string"><datavalue value="fa3bd744-11d5-3ce1-ad1a-0254f178f9b1" type="string" /></mainsnak><qualifiers /><qualifiers-order /><references><reference hash="73057782312f850e2ed69c4c28ad162f57f6d390"><snaks><property id="P248"><snak snaktype="value" property="P248" datatype="wikibase-item"><datavalue type="wikibase-entityid"><value entity-type="item" numeric-id="14005" /></datavalue></snak></property></snaks><snaks-order><property>P248</property></snaks-order></reference></references></claim></property><property id="P1566"><claim id="Q27561$28CED1A4-2490-4F83-B40B-3E3EF9A27B47" type="statement" rank="normal"><mainsnak snaktype="value" property="P1566" datatype="string"><datavalue value="7626844" type="string" /></mainsnak><qualifiers /><qualifiers-order /></claim></property></claims><sitelinks><sitelink site="plwiki" title="Holandia Karaibska"><badges /></sitelink><sitelink site="euwiki" title="Karibeko Herbehereak"><badges /></sitelink><sitelink site="kowiki" title="네덜란드령 카리브"><badges /></sitelink><sitelink site="frwiki" title="Pays-Bas caribéens"><badges /></sitelink><sitelink site="bswiki" title="Karipska Holandija"><badges /></sitelink><sitelink site="eswiki" title="Caribe Neerlandés"><badges /></sitelink><sitelink site="ladwiki" title="Karibe Neerlandez"><badges /></sitelink><sitelink site="frrwiki" title="BES-eilunen"><badges /></sitelink><sitelink site="afwiki" title="Karibies Nederland"><badges /></sitelink><sitelink site="ocwiki" title="Païses Basses Caribencs"><badges /></sitelink><sitelink site="lvwiki" title="Bonaire, Sintēstatiusa un Saba"><badges /></sitelink><sitelink site="itwiki" title="Isole BES"><badges /></sitelink><sitelink site="idwiki" title="Belanda Karibia"><badges /></sitelink><sitelink site="dewiki" title="Besondere Gemeinde (Niederlande)"><badges /></sitelink><sitelink site="jawiki" title="ボネール、シント・ユースタティウスおよびサバ"><badges /></sitelink><sitelink site="viwiki" title="Caribe Hà Lan"><badges /></sitelink><sitelink site="svwiki" title="Karibiska Nederländerna"><badges /></sitelink><sitelink site="nlwiki" title="Caribisch Nederland"><badges /></sitelink><sitelink site="ptwiki" title="Países Baixos Caribenhos"><badges /></sitelink><sitelink site="ruwiki" title="Бонэйр, Синт-Эстатиус и Саба"><badges /></sitelink><sitelink site="srwiki" title="Карипска Холандија"><badges /></sitelink><sitelink site="enwiki" title="Caribbean Netherlands"><badges /></sitelink><sitelink site="fywiki" title="Karibysk Nederlân"><badges /></sitelink><sitelink site="nowiki" title="Karibisk Nederland"><badges /></sitelink><sitelink site="cawiki" title="Illes BES"><badges /></sitelink><sitelink site="ukwiki" title="Нідерландські Карибські острови"><badges /></sitelink><sitelink site="nnwiki" title="Karibisk Nederland"><badges /></sitelink><sitelink site="cswiki" title="Karibské Nizozemsko"><badges /></sitelink><sitelink site="fawiki" title="جزایر کارائیب هلند"><badges /></sitelink><sitelink site="urwiki" title="کیریبین نیدرلینڈز"><badges /></sitelink><sitelink site="ltwiki" title="BES salos"><badges /></sitelink><sitelink site="arwiki" title="الجزر الكاريبية الهولندية"><badges /></sitelink><sitelink site="eowiki" title="Kariba Nederlando"><badges /></sitelink><sitelink site="pnbwiki" title="کریبین نیدرلینڈز"><badges /></sitelink><sitelink site="pawiki" title="ਕੈਰੀਬੀਆਈ ਨੀਦਰਲੈਂਡ"><badges /></sitelink><sitelink site="liwiki" title="Caribisch Nederland"><badges /></sitelink><sitelink site="simplewiki" title="Caribbean Netherlands"><badges /></sitelink><sitelink site="elwiki" title="BES νησιά"><badges /></sitelink><sitelink site="zhwiki" title="荷蘭加勒比區"><badges /></sitelink><sitelink site="kawiki" title="კარიბის ნიდერლანდი"><badges /></sitelink><sitelink site="huwiki" title="Karibi Hollandia"><badges /></sitelink></sitelinks></entity></entities></entity>